slicevision/__init__.py
slicevision/annotation.py
slicevision/model.py
slicevision/predict.py
slicevision/prediction.py
slicevision/slicing.py
slicevision-0.1.0.dist-info/LICENSE
slicevision-0.1.0.dist-info/METADATA
slicevision-0.1.0.dist-info/WHEEL
slicevision-0.1.0.dist-info/top_level.txt
slicevision-0.1.0.dist-info/RECORD
