Metadata-Version: 2.1
Name: slicevision
Version: 0.1.0
Summary: A vision library for performing sliced inference on large images/small objects
Home-page: https://github.com/obss/slicevision
Author: OBSS
License: MIT
Platform: UNKNOWN
Classifier: License :: OSI Approved :: MIT License
Classifier: Operating System :: OS Independent
Classifier: Intended Audience :: Developers
Classifier: Intended Audience :: Science/Research
Classifier: Programming Language :: Python :: 3
Classifier: Programming Language :: Python :: 3.6
Classifier: Programming Language :: Python :: 3.7
Classifier: Programming Language :: Python :: 3.8
Classifier: Topic :: Software Development :: Libraries
Classifier: Topic :: Software Development :: Libraries :: Python Modules
Requires-Python: >=3.6
Requires-Dist: opencv-python (>=4.2.0.32)
Requires-Dist: shapely (>=1.7.0)
Requires-Dist: tqdm (>=4.48.2)
Requires-Dist: imantics (>=0.1.12)
Requires-Dist: scikit-image (>=0.14.2)
Provides-Extra: tests
Requires-Dist: pytest ; extra == 'tests'
Requires-Dist: mmdet ; extra == 'tests'
